CHANGES.txt
MANIFEST.in
README.rst
setup.cfg
setup.py
src/collective/__init__.py
src/collective.whoiswho.egg-info/PKG-INFO
src/collective.whoiswho.egg-info/SOURCES.txt
src/collective.whoiswho.egg-info/dependency_links.txt
src/collective.whoiswho.egg-info/entry_points.txt
src/collective.whoiswho.egg-info/namespace_packages.txt
src/collective.whoiswho.egg-info/not-zip-safe
src/collective.whoiswho.egg-info/requires.txt
src/collective.whoiswho.egg-info/top_level.txt
src/collective/whoiswho/__init__.py
src/collective/whoiswho/configure.zcml
src/collective/whoiswho/browser/__init__.py
src/collective/whoiswho/browser/configure.zcml
src/collective/whoiswho/browser/interfaces.py
src/collective/whoiswho/browser/views.py
src/collective/whoiswho/browser/who_group_members.pt
src/collective/whoiswho/browser/who_is_who.pt
src/collective/whoiswho/browser/who_member.pt
src/collective/whoiswho/browser/who_member_details.pt
src/collective/whoiswho/profiles/default/actions.xml
src/collective/whoiswho/profiles/default/browserlayer.xml
src/collective/whoiswho/profiles/default/metadata.xml
src/collective/whoiswho/profiles/default/rolemap.xml