Metadata-Version: 1.1
Name: collective.whoiswho
Version: 1.0
Summary: Display members and groups
Home-page: http://svn.plone.org/svn/collective/
Author: Godefroid Chapelle
Author-email: gotcha@bubblenet.be
License: gpl
Platform: UNKNOWN
Classifier: Programming Language :: Python
Classifier: Programming Language :: Python :: 2.6
Classifier: Framework :: Plone
Classifier: Framework :: Plone :: 4.2
